fits/NestedLmfit.py
fits/__init__.py
fits/poly_yamamura.py
fits/polynomial.py
statistics/GENERIC.py
statistics/__init__.py
statistics/base_moments.py
statistics/distribution_projections.py
wrappers/GENERIC.py
wrappers/PARCAS.py
wrappers/SDTRIMSP.py
wrappers/TRI3DST.py
wrappers/__init__.py
pycraters-0.0.4.dist-info/LICENSE
pycraters-0.0.4.dist-info/METADATA
pycraters-0.0.4.dist-info/WHEEL
pycraters-0.0.4.dist-info/top_level.txt
pycraters-0.0.4.dist-info/RECORD
